pygeohash_fast-0.3.0.dist-info/METADATA
pygeohash_fast-0.3.0.dist-info/WHEEL
pygeohash_fast-0.3.0.dist-info/license_files/LICENSE.md
pygeohash_fast/__init__.py
pygeohash_fast/pygeohash_fast.abi3.so
pygeohash_fast-0.3.0.dist-info/RECORD
